[
    {
        "comment": "/**\n * A field editor for specifying one of the selected languages\n *\n * @description Example:\n * <pre>\n * {\n *     \"myLanguage\": {\n *         \"label\": \"My language\",\n *         \"tabId\": \"content\",\n *         \"schemaId\": \"language\"\n *     }\n * }\n * </pre>\n *\n * @memberof HashBrown.Client.Views.Editors.FieldEditors\n */",
        "meta": {
            "range": [
                335,
                1315
            ],
            "filename": "LanguageEditor.js",
            "lineno": 19,
            "columnno": 0,
            "path": "/home/mrzapp/Development/Web/hashbrown-cms/src/Client/Views/Editors/FieldEditors",
            "code": {
                "id": "astnode100000004",
                "name": "LanguageEditor",
                "type": "ClassDeclaration",
                "paramnames": [
                    "params"
                ]
            }
        },
        "classdesc": "A field editor for specifying one of the selected languages",
        "description": "Example:\n<pre>\n{\n    \"myLanguage\": {\n        \"label\": \"My language\",\n        \"tabId\": \"content\",\n        \"schemaId\": \"language\"\n    }\n}\n</pre>",
        "memberof": "HashBrown.Client.Views.Editors.FieldEditors",
        "name": "LanguageEditor",
        "longname": "HashBrown.Client.Views.Editors.FieldEditors.LanguageEditor",
        "kind": "class",
        "scope": "static",
        "params": []
    },
    {
        "comment": "/**\n     * Constructor\n     */",
        "meta": {
            "range": [
                454,
                527
            ],
            "filename": "LanguageEditor.js",
            "lineno": 23,
            "columnno": 4,
            "path": "/home/mrzapp/Development/Web/hashbrown-cms/src/Client/Views/Editors/FieldEditors",
            "code": {
                "id": "astnode100000016",
                "name": "LanguageEditor",
                "type": "MethodDefinition",
                "paramnames": [
                    "params"
                ]
            },
            "vars": {
                "": null
            }
        },
        "description": "Constructor",
        "name": "LanguageEditor",
        "longname": "HashBrown.Client.Views.Editors.FieldEditors~LanguageEditor",
        "kind": "class",
        "memberof": "HashBrown.Client.Views.Editors.FieldEditors",
        "scope": "inner",
        "params": [],
        "undocumented": true
    },
    {
        "comment": "/**\n     * Prerender\n     */",
        "meta": {
            "range": [
                566,
                769
            ],
            "filename": "LanguageEditor.js",
            "lineno": 32,
            "columnno": 4,
            "path": "/home/mrzapp/Development/Web/hashbrown-cms/src/Client/Views/Editors/FieldEditors",
            "code": {
                "id": "astnode100000030",
                "name": "LanguageEditor#prerender",
                "type": "MethodDefinition",
                "paramnames": []
            },
            "vars": {
                "": null
            }
        },
        "description": "Prerender",
        "name": "prerender",
        "longname": "HashBrown.Client.Views.Editors.FieldEditors.LanguageEditor#prerender",
        "kind": "function",
        "memberof": "HashBrown.Client.Views.Editors.FieldEditors.LanguageEditor",
        "scope": "instance",
        "params": []
    },
    {
        "comment": "",
        "meta": {
            "range": [
                592,
                653
            ],
            "filename": "LanguageEditor.js",
            "lineno": 33,
            "columnno": 12,
            "path": "/home/mrzapp/Development/Web/hashbrown-cms/src/Client/Views/Editors/FieldEditors",
            "code": {
                "id": "astnode100000035",
                "name": "options",
                "type": "CallExpression",
                "value": ""
            }
        },
        "undocumented": true,
        "name": "options",
        "longname": "<anonymous>~options",
        "kind": "member",
        "memberof": "<anonymous>",
        "scope": "inner",
        "params": []
    },
    {
        "comment": "",
        "meta": {
            "range": [
                729,
                752
            ],
            "filename": "LanguageEditor.js",
            "lineno": 36,
            "columnno": 12,
            "path": "/home/mrzapp/Development/Web/hashbrown-cms/src/Client/Views/Editors/FieldEditors",
            "code": {
                "id": "astnode100000062",
                "name": "this.value",
                "type": "MemberExpression",
                "value": "options[0]",
                "paramnames": []
            }
        },
        "undocumented": true,
        "name": "value",
        "longname": "HashBrown.Client.Views.Editors.FieldEditors.LanguageEditor#value",
        "kind": "member",
        "memberof": "HashBrown.Client.Views.Editors.FieldEditors.LanguageEditor",
        "scope": "instance"
    },
    {
        "comment": "/**\n     * Renders this editor\n     */",
        "meta": {
            "range": [
                818,
                1313
            ],
            "filename": "LanguageEditor.js",
            "lineno": 43,
            "columnno": 4,
            "path": "/home/mrzapp/Development/Web/hashbrown-cms/src/Client/Views/Editors/FieldEditors",
            "code": {
                "id": "astnode100000069",
                "name": "LanguageEditor#template",
                "type": "MethodDefinition",
                "paramnames": []
            },
            "vars": {
                "": null
            }
        },
        "description": "Renders this editor",
        "name": "template",
        "longname": "HashBrown.Client.Views.Editors.FieldEditors.LanguageEditor#template",
        "kind": "function",
        "memberof": "HashBrown.Client.Views.Editors.FieldEditors.LanguageEditor",
        "scope": "instance",
        "params": []
    },
    {
        "comment": "",
        "meta": {
            "range": [
                853,
                897
            ],
            "filename": "LanguageEditor.js",
            "lineno": 44,
            "columnno": 22,
            "path": "/home/mrzapp/Development/Web/hashbrown-cms/src/Client/Views/Editors/FieldEditors",
            "code": {
                "id": "astnode100000079",
                "name": "class",
                "type": "Literal",
                "value": "field-editor field-editor--language"
            }
        },
        "undocumented": true,
        "name": "class",
        "longname": "class",
        "kind": "member",
        "scope": "global"
    },
    {
        "comment": "",
        "meta": {
            "range": [
                967,
                984
            ],
            "filename": "LanguageEditor.js",
            "lineno": 46,
            "columnno": 16,
            "path": "/home/mrzapp/Development/Web/hashbrown-cms/src/Client/Views/Editors/FieldEditors",
            "code": {
                "id": "astnode100000091",
                "name": "value",
                "type": "MemberExpression",
                "value": "this.value"
            }
        },
        "undocumented": true,
        "name": "value",
        "longname": "value",
        "kind": "member",
        "scope": "global"
    },
    {
        "comment": "",
        "meta": {
            "range": [
                1002,
                1062
            ],
            "filename": "LanguageEditor.js",
            "lineno": 47,
            "columnno": 16,
            "path": "/home/mrzapp/Development/Web/hashbrown-cms/src/Client/Views/Editors/FieldEditors",
            "code": {
                "id": "astnode100000095",
                "name": "options",
                "type": "CallExpression",
                "value": ""
            }
        },
        "undocumented": true,
        "name": "options",
        "longname": "options",
        "kind": "member",
        "scope": "global"
    },
    {
        "comment": "",
        "meta": {
            "range": [
                1080,
                1111
            ],
            "filename": "LanguageEditor.js",
            "lineno": 48,
            "columnno": 16,
            "path": "/home/mrzapp/Development/Web/hashbrown-cms/src/Client/Views/Editors/FieldEditors",
            "code": {
                "id": "astnode100000104",
                "name": "tooltip",
                "type": "LogicalExpression",
                "value": ""
            }
        },
        "undocumented": true,
        "name": "tooltip",
        "longname": "tooltip",
        "kind": "member",
        "scope": "global"
    },
    {
        "comment": "",
        "meta": {
            "range": [
                1129,
                1272
            ],
            "filename": "LanguageEditor.js",
            "lineno": 49,
            "columnno": 16,
            "path": "/home/mrzapp/Development/Web/hashbrown-cms/src/Client/Views/Editors/FieldEditors",
            "code": {
                "id": "astnode100000110",
                "name": "onChange",
                "type": "ArrowFunctionExpression"
            },
            "vars": {
                "this.value": "HashBrown.Client.Views.Editors.FieldEditors.LanguageEditor#value"
            }
        },
        "undocumented": true,
        "name": "onChange",
        "longname": "onChange",
        "kind": "function",
        "scope": "global"
    },
    {
        "comment": "",
        "meta": {
            "range": [
                1175,
                1196
            ],
            "filename": "LanguageEditor.js",
            "lineno": 50,
            "columnno": 20,
            "path": "/home/mrzapp/Development/Web/hashbrown-cms/src/Client/Views/Editors/FieldEditors",
            "code": {
                "id": "astnode100000115",
                "name": "this.value",
                "type": "Identifier",
                "value": "newValue",
                "paramnames": []
            }
        },
        "undocumented": true,
        "name": "value",
        "longname": "HashBrown.Client.Views.Editors.FieldEditors.LanguageEditor#value",
        "kind": "member",
        "memberof": "HashBrown.Client.Views.Editors.FieldEditors.LanguageEditor",
        "scope": "instance"
    },
    {
        "comment": "",
        "meta": {
            "range": [
                1317,
                1348
            ],
            "filename": "LanguageEditor.js",
            "lineno": 59,
            "columnno": 0,
            "path": "/home/mrzapp/Development/Web/hashbrown-cms/src/Client/Views/Editors/FieldEditors",
            "code": {
                "id": "astnode100000131",
                "name": "module.exports",
                "type": "Identifier",
                "value": "LanguageEditor",
                "paramnames": []
            }
        },
        "undocumented": true,
        "name": "exports",
        "longname": "module.exports",
        "kind": "member",
        "memberof": "module",
        "scope": "static"
    },
    {
        "kind": "package",
        "longname": "package:undefined",
        "files": [
            "/home/mrzapp/Development/Web/hashbrown-cms/src/Client/Views/Editors/FieldEditors/LanguageEditor.js"
        ]
    }
]
